{
  "meta": {
    "source_pdf": "FECHA01_inicial",
    "extracted_at_utc": "2025-10-31T16:42:09+00:00",
    "fechas_cumplidas": 0,
    "fechas_detectadas": [
      1
    ]
  },
  "standings": [
    {
      "pos": 1,
      "nro": 1,
      "nombre": "VALLEJOS Luciano",
      "anterior": 0.0,
      "serie": 0.0,
      "semif": 0.0,
      "prefinal": 0.0,
      "final": 0.0,
      "total": 0.0,
      "fin": null,
      "extras_raw": null
    },
    {
      "pos": 2,
      "nro": 2,
      "nombre": "FRANCHI Luciano",
      "anterior": 0.0,
      "serie": 0.0,
      "semif": 0.0,
      "prefinal": 0.0,
      "final": 0.0,
      "total": 0.0,
      "fin": null,
      "extras_raw": null
    },
    {
      "pos": 3,
      "nro": 3,
      "nombre": "PEREZ MELER Agustín",
      "anterior": 0.0,
      "serie": 0.0,
      "semif": 0.0,
      "prefinal": 0.0,
      "final": 0.0,
      "total": 0.0,
      "fin": null,
      "extras_raw": null
    },
    {
      "pos": 4,
      "nro": 4,
      "nombre": "ROTH Claudio",
      "anterior": 0.0,
      "serie": 0.0,
      "semif": 0.0,
      "prefinal": 0.0,
      "final": 0.0,
      "total": 0.0,
      "fin": null,
      "extras_raw": null
    },
    {
      "pos": 5,
      "nro": 5,
      "nombre": "ALTAMIRANO Roy",
      "anterior": 0.0,
      "serie": 0.0,
      "semif": 0.0,
      "prefinal": 0.0,
      "final": 0.0,
      "total": 0.0,
      "fin": null,
      "extras_raw": null
    },
    {
      "pos": 6,
      "nro": 6,
      "nombre": "BURGOS Sebastián",
      "anterior": 0.0,
      "serie": 0.0,
      "semif": 0.0,
      "prefinal": 0.0,
      "final": 0.0,
      "total": 0.0,
      "fin": null,
      "extras_raw": null
    },
    {
      "pos": 7,
      "nro": 7,
      "nombre": "ROTH Ezequiel",
      "anterior": 0.0,
      "serie": 0.0,
      "semif": 0.0,
      "prefinal": 0.0,
      "final": 0.0,
      "total": 0.0,
      "fin": null,
      "extras_raw": null
    },
    {
      "pos": 8,
      "nro": 8,
      "nombre": "ALTAMIRANO Kevin",
      "anterior": 0.0,
      "serie": 0.0,
      "semif": 0.0,
      "prefinal": 0.0,
      "final": 0.0,
      "total": 0.0,
      "fin": null,
      "extras_raw": null
    },
    {
      "pos": 9,
      "nro": 9,
      "nombre": "OYOLA Matías",
      "anterior": 0.0,
      "serie": 0.0,
      "semif": 0.0,
      "prefinal": 0.0,
      "final": 0.0,
      "total": 0.0,
      "fin": null,
      "extras_raw": null
    },
    {
      "pos": 10,
      "nro": 11,
      "nombre": "MANCINI Esteban",
      "anterior": 0.0,
      "serie": 0.0,
      "semif": 0.0,
      "prefinal": 0.0,
      "final": 0.0,
      "total": 0.0,
      "fin": null,
      "extras_raw": null
    },
    {
      "pos": 11,
      "nro": 12,
      "nombre": "REY Javier",
      "anterior": 0.0,
      "serie": 0.0,
      "semif": 0.0,
      "prefinal": 0.0,
      "final": 0.0,
      "total": 0.0,
      "fin": null,
      "extras_raw": null
    },
    {
      "pos": 12,
      "nro": 13,
      "nombre": "ROUAIX Javier",
      "anterior": 0.0,
      "serie": 0.0,
      "semif": 0.0,
      "prefinal": 0.0,
      "final": 0.0,
      "total": 0.0,
      "fin": null,
      "extras_raw": null
    },
    {
      "pos": 13,
      "nro": 14,
      "nombre": "SALDAMANDO Fernando",
      "anterior": 0.0,
      "serie": 0.0,
      "semif": 0.0,
      "prefinal": 0.0,
      "final": 0.0,
      "total": 0.0,
      "fin": null,
      "extras_raw": null
    },
    {
      "pos": 14,
      "nro": 15,
      "nombre": "HIDALGO Federico",
      "anterior": 0.0,
      "serie": 0.0,
      "semif": 0.0,
      "prefinal": 0.0,
      "final": 0.0,
      "total": 0.0,
      "fin": null,
      "extras_raw": null
    },
    {
      "pos": 15,
      "nro": 16,
      "nombre": "RODRIGUEZ Juan Cruz",
      "anterior": 0.0,
      "serie": 0.0,
      "semif": 0.0,
      "prefinal": 0.0,
      "final": 0.0,
      "total": 0.0,
      "fin": null,
      "extras_raw": null
    },
    {
      "pos": 16,
      "nro": 18,
      "nombre": "SCHIEBELBEIN Gabriel",
      "anterior": 0.0,
      "serie": 0.0,
      "semif": 0.0,
      "prefinal": 0.0,
      "final": 0.0,
      "total": 0.0,
      "fin": null,
      "extras_raw": null
    },
    {
      "pos": 17,
      "nro": 19,
      "nombre": "TODINO Juan",
      "anterior": 0.0,
      "serie": 0.0,
      "semif": 0.0,
      "prefinal": 0.0,
      "final": 0.0,
      "total": 0.0,
      "fin": null,
      "extras_raw": null
    },
    {
      "pos": 18,
      "nro": 20,
      "nombre": "PEREZ Sebastián",
      "anterior": 0.0,
      "serie": 0.0,
      "semif": 0.0,
      "prefinal": 0.0,
      "final": 0.0,
      "total": 0.0,
      "fin": null,
      "extras_raw": null
    },
    {
      "pos": 19,
      "nro": 21,
      "nombre": "SCHMIT Nahuel",
      "anterior": 0.0,
      "serie": 0.0,
      "semif": 0.0,
      "prefinal": 0.0,
      "final": 0.0,
      "total": 0.0,
      "fin": null,
      "extras_raw": null
    },
    {
      "pos": 20,
      "nro": 22,
      "nombre": "BONIVARDO Fernando",
      "anterior": 0.0,
      "serie": 0.0,
      "semif": 0.0,
      "prefinal": 0.0,
      "final": 0.0,
      "total": 0.0,
      "fin": null,
      "extras_raw": null
    },
    {
      "pos": 21,
      "nro": 23,
      "nombre": "PINEIRO Julio",
      "anterior": 0.0,
      "serie": 0.0,
      "semif": 0.0,
      "prefinal": 0.0,
      "final": 0.0,
      "total": 0.0,
      "fin": null,
      "extras_raw": null
    },
    {
      "pos": 22,
      "nro": 24,
      "nombre": "AUSILI Marcelo",
      "anterior": 0.0,
      "serie": 0.0,
      "semif": 0.0,
      "prefinal": 0.0,
      "final": 0.0,
      "total": 0.0,
      "fin": null,
      "extras_raw": null
    },
    {
      "pos": 23,
      "nro": 25,
      "nombre": "PALMA Nicolás",
      "anterior": 0.0,
      "serie": 0.0,
      "semif": 0.0,
      "prefinal": 0.0,
      "final": 0.0,
      "total": 0.0,
      "fin": null,
      "extras_raw": null
    },
    {
      "pos": 24,
      "nro": 26,
      "nombre": "BREZINA Gonzalo",
      "anterior": 0.0,
      "serie": 0.0,
      "semif": 0.0,
      "prefinal": 0.0,
      "final": 0.0,
      "total": 0.0,
      "fin": null,
      "extras_raw": null
    },
    {
      "pos": 25,
      "nro": 27,
      "nombre": "AUSILI Agustín",
      "anterior": 0.0,
      "serie": 0.0,
      "semif": 0.0,
      "prefinal": 0.0,
      "final": 0.0,
      "total": 0.0,
      "fin": null,
      "extras_raw": null
    },
    {
      "pos": 26,
      "nro": 28,
      "nombre": "ANASTASIO Nicolás",
      "anterior": 0.0,
      "serie": 0.0,
      "semif": 0.0,
      "prefinal": 0.0,
      "final": 0.0,
      "total": 0.0,
      "fin": null,
      "extras_raw": null
    },
    {
      "pos": 27,
      "nro": 29,
      "nombre": "GARCIA LOPEZ Joaquín",
      "anterior": 0.0,
      "serie": 0.0,
      "semif": 0.0,
      "prefinal": 0.0,
      "final": 0.0,
      "total": 0.0,
      "fin": null,
      "extras_raw": null
    },
    {
      "pos": 28,
      "nro": 30,
      "nombre": "RESOLA Jonathan",
      "anterior": 0.0,
      "serie": 0.0,
      "semif": 0.0,
      "prefinal": 0.0,
      "final": 0.0,
      "total": 0.0,
      "fin": null,
      "extras_raw": null
    },
    {
      "pos": 29,
      "nro": 31,
      "nombre": "PUCCINELLI Carlos",
      "anterior": 0.0,
      "serie": 0.0,
      "semif": 0.0,
      "prefinal": 0.0,
      "final": 0.0,
      "total": 0.0,
      "fin": null,
      "extras_raw": null
    },
    {
      "pos": 30,
      "nro": 32,
      "nombre": "MELGER Julian",
      "anterior": 0.0,
      "serie": 0.0,
      "semif": 0.0,
      "prefinal": 0.0,
      "final": 0.0,
      "total": 0.0,
      "fin": null,
      "extras_raw": null
    },
    {
      "pos": 31,
      "nro": 33,
      "nombre": "CAPUTO Nicolás",
      "anterior": 0.0,
      "serie": 0.0,
      "semif": 0.0,
      "prefinal": 0.0,
      "final": 0.0,
      "total": 0.0,
      "fin": null,
      "extras_raw": null
    },
    {
      "pos": 32,
      "nro": 34,
      "nombre": "DAILOFF Nehuen",
      "anterior": 0.0,
      "serie": 0.0,
      "semif": 0.0,
      "prefinal": 0.0,
      "final": 0.0,
      "total": 0.0,
      "fin": null,
      "extras_raw": null
    },
    {
      "pos": 33,
      "nro": 35,
      "nombre": "MORENO Maximiliano",
      "anterior": 0.0,
      "serie": 0.0,
      "semif": 0.0,
      "prefinal": 0.0,
      "final": 0.0,
      "total": 0.0,
      "fin": null,
      "extras_raw": null
    },
    {
      "pos": 34,
      "nro": 36,
      "nombre": "MACAZAGA Nicolas",
      "anterior": 0.0,
      "serie": 0.0,
      "semif": 0.0,
      "prefinal": 0.0,
      "final": 0.0,
      "total": 0.0,
      "fin": null,
      "extras_raw": null
    },
    {
      "pos": 35,
      "nro": 38,
      "nombre": "MADRIL Braian",
      "anterior": 0.0,
      "serie": 0.0,
      "semif": 0.0,
      "prefinal": 0.0,
      "final": 0.0,
      "total": 0.0,
      "fin": null,
      "extras_raw": null
    },
    {
      "pos": 36,
      "nro": 39,
      "nombre": "PAGLIALUNGA Eros",
      "anterior": 0.0,
      "serie": 0.0,
      "semif": 0.0,
      "prefinal": 0.0,
      "final": 0.0,
      "total": 0.0,
      "fin": null,
      "extras_raw": null
    },
    {
      "pos": 37,
      "nro": 40,
      "nombre": "BALDUCHI Valentin",
      "anterior": 0.0,
      "serie": 0.0,
      "semif": 0.0,
      "prefinal": 0.0,
      "final": 0.0,
      "total": 0.0,
      "fin": null,
      "extras_raw": null
    },
    {
      "pos": 38,
      "nro": 41,
      "nombre": "CUTINI Santino",
      "anterior": 0.0,
      "serie": 0.0,
      "semif": 0.0,
      "prefinal": 0.0,
      "final": 0.0,
      "total": 0.0,
      "fin": null,
      "extras_raw": null
    },
    {
      "pos": 39,
      "nro": 43,
      "nombre": "COLTURI Fabian",
      "anterior": 0.0,
      "serie": 0.0,
      "semif": 0.0,
      "prefinal": 0.0,
      "final": 0.0,
      "total": 0.0,
      "fin": null,
      "extras_raw": null
    },
    {
      "pos": 40,
      "nro": 44,
      "nombre": "MARCOS Nehuen",
      "anterior": 0.0,
      "serie": 0.0,
      "semif": 0.0,
      "prefinal": 0.0,
      "final": 0.0,
      "total": 0.0,
      "fin": null,
      "extras_raw": null
    },
    {
      "pos": 41,
      "nro": 45,
      "nombre": "PETRACCI Gaston",
      "anterior": 0.0,
      "serie": 0.0,
      "semif": 0.0,
      "prefinal": 0.0,
      "final": 0.0,
      "total": 0.0,
      "fin": null,
      "extras_raw": null
    },
    {
      "pos": 42,
      "nro": 46,
      "nombre": "DUPONT Braian",
      "anterior": 0.0,
      "serie": 0.0,
      "semif": 0.0,
      "prefinal": 0.0,
      "final": 0.0,
      "total": 0.0,
      "fin": null,
      "extras_raw": null
    },
    {
      "pos": 43,
      "nro": 47,
      "nombre": "CUTINI Gustavo",
      "anterior": 0.0,
      "serie": 0.0,
      "semif": 0.0,
      "prefinal": 0.0,
      "final": 0.0,
      "total": 0.0,
      "fin": null,
      "extras_raw": null
    },
    {
      "pos": 44,
      "nro": 48,
      "nombre": "YUROVSKY Guillermo",
      "anterior": 0.0,
      "serie": 0.0,
      "semif": 0.0,
      "prefinal": 0.0,
      "final": 0.0,
      "total": 0.0,
      "fin": null,
      "extras_raw": null
    },
    {
      "pos": 45,
      "nro": 49,
      "nombre": "PERUGINI Flavio",
      "anterior": 0.0,
      "serie": 0.0,
      "semif": 0.0,
      "prefinal": 0.0,
      "final": 0.0,
      "total": 0.0,
      "fin": null,
      "extras_raw": null
    },
    {
      "pos": 46,
      "nro": 50,
      "nombre": "ANDRADE Joaquin",
      "anterior": 0.0,
      "serie": 0.0,
      "semif": 0.0,
      "prefinal": 0.0,
      "final": 0.0,
      "total": 0.0,
      "fin": null,
      "extras_raw": null
    },
    {
      "pos": 47,
      "nro": 51,
      "nombre": "ONORATO Nicolas",
      "anterior": 0.0,
      "serie": 0.0,
      "semif": 0.0,
      "prefinal": 0.0,
      "final": 0.0,
      "total": 0.0,
      "fin": null,
      "extras_raw": null
    },
    {
      "pos": 48,
      "nro": 53,
      "nombre": "PASCUAL Emanuel",
      "anterior": 0.0,
      "serie": 0.0,
      "semif": 0.0,
      "prefinal": 0.0,
      "final": 0.0,
      "total": 0.0,
      "fin": null,
      "extras_raw": null
    },
    {
      "pos": 49,
      "nro": 54,
      "nombre": "TOLEDO Joaquin",
      "anterior": 0.0,
      "serie": 0.0,
      "semif": 0.0,
      "prefinal": 0.0,
      "final": 0.0,
      "total": 0.0,
      "fin": null,
      "extras_raw": null
    },
    {
      "pos": 50,
      "nro": 55,
      "nombre": "ANTINORI Axel",
      "anterior": 0.0,
      "serie": 0.0,
      "semif": 0.0,
      "prefinal": 0.0,
      "final": 0.0,
      "total": 0.0,
      "fin": null,
      "extras_raw": null
    },
    {
      "pos": 51,
      "nro": 56,
      "nombre": "CHIAPPARO Nicolas",
      "anterior": 0.0,
      "serie": 0.0,
      "semif": 0.0,
      "prefinal": 0.0,
      "final": 0.0,
      "total": 0.0,
      "fin": null,
      "extras_raw": null
    },
    {
      "pos": 52,
      "nro": 57,
      "nombre": "RAZQUIN Gonzalo",
      "anterior": 0.0,
      "serie": 0.0,
      "semif": 0.0,
      "prefinal": 0.0,
      "final": 0.0,
      "total": 0.0,
      "fin": null,
      "extras_raw": null
    },
    {
      "pos": 53,
      "nro": 58,
      "nombre": "PEREZ Marcelo",
      "anterior": 0.0,
      "serie": 0.0,
      "semif": 0.0,
      "prefinal": 0.0,
      "final": 0.0,
      "total": 0.0,
      "fin": null,
      "extras_raw": null
    },
    {
      "pos": 54,
      "nro": 60,
      "nombre": "MOYANO Antonio",
      "anterior": 0.0,
      "serie": 0.0,
      "semif": 0.0,
      "prefinal": 0.0,
      "final": 0.0,
      "total": 0.0,
      "fin": null,
      "extras_raw": null
    },
    {
      "pos": 55,
      "nro": 63,
      "nombre": "JACA Aaron",
      "anterior": 0.0,
      "serie": 0.0,
      "semif": 0.0,
      "prefinal": 0.0,
      "final": 0.0,
      "total": 0.0,
      "fin": null,
      "extras_raw": null
    },
    {
      "pos": 56,
      "nro": 64,
      "nombre": "BLANC Lucas",
      "anterior": 0.0,
      "serie": 0.0,
      "semif": 0.0,
      "prefinal": 0.0,
      "final": 0.0,
      "total": 0.0,
      "fin": null,
      "extras_raw": null
    },
    {
      "pos": 57,
      "nro": 65,
      "nombre": "ALZA Pablo",
      "anterior": 0.0,
      "serie": 0.0,
      "semif": 0.0,
      "prefinal": 0.0,
      "final": 0.0,
      "total": 0.0,
      "fin": null,
      "extras_raw": null
    },
    {
      "pos": 58,
      "nro": 66,
      "nombre": "YUNGBLUT Valentin",
      "anterior": 0.0,
      "serie": 0.0,
      "semif": 0.0,
      "prefinal": 0.0,
      "final": 0.0,
      "total": 0.0,
      "fin": null,
      "extras_raw": null
    },
    {
      "pos": 59,
      "nro": 68,
      "nombre": "HOCK Gaston",
      "anterior": 0.0,
      "serie": 0.0,
      "semif": 0.0,
      "prefinal": 0.0,
      "final": 0.0,
      "total": 0.0,
      "fin": null,
      "extras_raw": null
    },
    {
      "pos": 60,
      "nro": 69,
      "nombre": "OVEJERO Facundo",
      "anterior": 0.0,
      "serie": 0.0,
      "semif": 0.0,
      "prefinal": 0.0,
      "final": 0.0,
      "total": 0.0,
      "fin": null,
      "extras_raw": null
    },
    {
      "pos": 61,
      "nro": 72,
      "nombre": "JACOB Ruben",
      "anterior": 0.0,
      "serie": 0.0,
      "semif": 0.0,
      "prefinal": 0.0,
      "final": 0.0,
      "total": 0.0,
      "fin": null,
      "extras_raw": null
    },
    {
      "pos": 62,
      "nro": 74,
      "nombre": "MANZOTTI Gustavo",
      "anterior": 0.0,
      "serie": 0.0,
      "semif": 0.0,
      "prefinal": 0.0,
      "final": 0.0,
      "total": 0.0,
      "fin": null,
      "extras_raw": null
    },
    {
      "pos": 63,
      "nro": 75,
      "nombre": "BENITEZ Gaston",
      "anterior": 0.0,
      "serie": 0.0,
      "semif": 0.0,
      "prefinal": 0.0,
      "final": 0.0,
      "total": 0.0,
      "fin": null,
      "extras_raw": null
    },
    {
      "pos": 64,
      "nro": 76,
      "nombre": "LOPEZ Brian",
      "anterior": 0.0,
      "serie": 0.0,
      "semif": 0.0,
      "prefinal": 0.0,
      "final": 0.0,
      "total": 0.0,
      "fin": null,
      "extras_raw": null
    },
    {
      "pos": 65,
      "nro": 78,
      "nombre": "GONZALEZ Juan",
      "anterior": 0.0,
      "serie": 0.0,
      "semif": 0.0,
      "prefinal": 0.0,
      "final": 0.0,
      "total": 0.0,
      "fin": null,
      "extras_raw": null
    },
    {
      "pos": 66,
      "nro": 79,
      "nombre": "LUCERO Sebastian",
      "anterior": 0.0,
      "serie": 0.0,
      "semif": 0.0,
      "prefinal": 0.0,
      "final": 0.0,
      "total": 0.0,
      "fin": null,
      "extras_raw": null
    },
    {
      "pos": 67,
      "nro": 81,
      "nombre": "CALVO Jose Maria",
      "anterior": 0.0,
      "serie": 0.0,
      "semif": 0.0,
      "prefinal": 0.0,
      "final": 0.0,
      "total": 0.0,
      "fin": null,
      "extras_raw": null
    },
    {
      "pos": 68,
      "nro": 86,
      "nombre": "SALAZAR Alfredo",
      "anterior": 0.0,
      "serie": 0.0,
      "semif": 0.0,
      "prefinal": 0.0,
      "final": 0.0,
      "total": 0.0,
      "fin": null,
      "extras_raw": null
    },
    {
      "pos": 69,
      "nro": 88,
      "nombre": "SOTO Juan Maria",
      "anterior": 0.0,
      "serie": 0.0,
      "semif": 0.0,
      "prefinal": 0.0,
      "final": 0.0,
      "total": 0.0,
      "fin": null,
      "extras_raw": null
    },
    {
      "pos": 70,
      "nro": 93,
      "nombre": "BATISTELI Raul",
      "anterior": 0.0,
      "serie": 0.0,
      "semif": 0.0,
      "prefinal": 0.0,
      "final": 0.0,
      "total": 0.0,
      "fin": null,
      "extras_raw": null
    },
    {
      "pos": 71,
      "nro": 94,
      "nombre": "CHIESA Alejandro",
      "anterior": 0.0,
      "serie": 0.0,
      "semif": 0.0,
      "prefinal": 0.0,
      "final": 0.0,
      "total": 0.0,
      "fin": null,
      "extras_raw": null
    },
    {
      "pos": 72,
      "nro": 95,
      "nombre": "PALLOTTI Ivan",
      "anterior": 0.0,
      "serie": 0.0,
      "semif": 0.0,
      "prefinal": 0.0,
      "final": 0.0,
      "total": 0.0,
      "fin": null,
      "extras_raw": null
    },
    {
      "pos": 73,
      "nro": 96,
      "nombre": "BECCHIO Martin",
      "anterior": 0.0,
      "serie": 0.0,
      "semif": 0.0,
      "prefinal": 0.0,
      "final": 0.0,
      "total": 0.0,
      "fin": null,
      "extras_raw": null
    },
    {
      "pos": 74,
      "nro": 97,
      "nombre": "SOTO Gaston",
      "anterior": 0.0,
      "serie": 0.0,
      "semif": 0.0,
      "prefinal": 0.0,
      "final": 0.0,
      "total": 0.0,
      "fin": null,
      "extras_raw": null
    },
    {
      "pos": 75,
      "nro": 98,
      "nombre": "FRITZ Jorge",
      "anterior": 0.0,
      "serie": 0.0,
      "semif": 0.0,
      "prefinal": 0.0,
      "final": 0.0,
      "total": 0.0,
      "fin": null,
      "extras_raw": null
    },
    {
      "pos": 76,
      "nro": 101,
      "nombre": "DOMINGUEZ Carlos",
      "anterior": 0.0,
      "serie": 0.0,
      "semif": 0.0,
      "prefinal": 0.0,
      "final": 0.0,
      "total": 0.0,
      "fin": null,
      "extras_raw": null
    },
    {
      "pos": 77,
      "nro": 102,
      "nombre": "TORRES Luciano",
      "anterior": 0.0,
      "serie": 0.0,
      "semif": 0.0,
      "prefinal": 0.0,
      "final": 0.0,
      "total": 0.0,
      "fin": null,
      "extras_raw": null
    },
    {
      "pos": 78,
      "nro": 104,
      "nombre": "HARDOY Maximiliano",
      "anterior": 0.0,
      "serie": 0.0,
      "semif": 0.0,
      "prefinal": 0.0,
      "final": 0.0,
      "total": 0.0,
      "fin": null,
      "extras_raw": null
    },
    {
      "pos": 79,
      "nro": 105,
      "nombre": "ZABALEGUI Martin",
      "anterior": 0.0,
      "serie": 0.0,
      "semif": 0.0,
      "prefinal": 0.0,
      "final": 0.0,
      "total": 0.0,
      "fin": null,
      "extras_raw": null
    },
    {
      "pos": 80,
      "nro": 107,
      "nombre": "HASPERT Juan",
      "anterior": 0.0,
      "serie": 0.0,
      "semif": 0.0,
      "prefinal": 0.0,
      "final": 0.0,
      "total": 0.0,
      "fin": null,
      "extras_raw": null
    },
    {
      "pos": 81,
      "nro": 108,
      "nombre": "FORNERON Carlos",
      "anterior": 0.0,
      "serie": 0.0,
      "semif": 0.0,
      "prefinal": 0.0,
      "final": 0.0,
      "total": 0.0,
      "fin": null,
      "extras_raw": null
    },
    {
      "pos": 82,
      "nro": 109,
      "nombre": "ANASTASIO Diego",
      "anterior": 0.0,
      "serie": 0.0,
      "semif": 0.0,
      "prefinal": 0.0,
      "final": 0.0,
      "total": 0.0,
      "fin": null,
      "extras_raw": null
    },
    {
      "pos": 83,
      "nro": 110,
      "nombre": "FORD Lautaro",
      "anterior": 0.0,
      "serie": 0.0,
      "semif": 0.0,
      "prefinal": 0.0,
      "final": 0.0,
      "total": 0.0,
      "fin": null,
      "extras_raw": null
    },
    {
      "pos": 84,
      "nro": 111,
      "nombre": "BRAY Juan Pablo",
      "anterior": 0.0,
      "serie": 0.0,
      "semif": 0.0,
      "prefinal": 0.0,
      "final": 0.0,
      "total": 0.0,
      "fin": null,
      "extras_raw": null
    },
    {
      "pos": 85,
      "nro": 112,
      "nombre": "GOMEZ Agustin",
      "anterior": 0.0,
      "serie": 0.0,
      "semif": 0.0,
      "prefinal": 0.0,
      "final": 0.0,
      "total": 0.0,
      "fin": null,
      "extras_raw": null
    },
    {
      "pos": 86,
      "nro": 113,
      "nombre": "MARCO Gabriel",
      "anterior": 0.0,
      "serie": 0.0,
      "semif": 0.0,
      "prefinal": 0.0,
      "final": 0.0,
      "total": 0.0,
      "fin": null,
      "extras_raw": null
    },
    {
      "pos": 87,
      "nro": 114,
      "nombre": "CALVO Juan",
      "anterior": 0.0,
      "serie": 0.0,
      "semif": 0.0,
      "prefinal": 0.0,
      "final": 0.0,
      "total": 0.0,
      "fin": null,
      "extras_raw": null
    },
    {
      "pos": 88,
      "nro": 115,
      "nombre": "LOPEZ Agustin",
      "anterior": 0.0,
      "serie": 0.0,
      "semif": 0.0,
      "prefinal": 0.0,
      "final": 0.0,
      "total": 0.0,
      "fin": null,
      "extras_raw": null
    },
    {
      "pos": 89,
      "nro": 116,
      "nombre": "ZUBELDIA Rodrigo",
      "anterior": 0.0,
      "serie": 0.0,
      "semif": 0.0,
      "prefinal": 0.0,
      "final": 0.0,
      "total": 0.0,
      "fin": null,
      "extras_raw": null
    },
    {
      "pos": 90,
      "nro": 123,
      "nombre": "COLANERI Agustin",
      "anterior": 0.0,
      "serie": 0.0,
      "semif": 0.0,
      "prefinal": 0.0,
      "final": 0.0,
      "total": 0.0,
      "fin": null,
      "extras_raw": null
    },
    {
      "pos": 91,
      "nro": 127,
      "nombre": "GRILL Lucas",
      "anterior": 0.0,
      "serie": 0.0,
      "semif": 0.0,
      "prefinal": 0.0,
      "final": 0.0,
      "total": 0.0,
      "fin": null,
      "extras_raw": null
    },
    {
      "pos": 92,
      "nro": 134,
      "nombre": "MONTANARI Nicolas",
      "anterior": 0.0,
      "serie": 0.0,
      "semif": 0.0,
      "prefinal": 0.0,
      "final": 0.0,
      "total": 0.0,
      "fin": null,
      "extras_raw": null
    },
    {
      "pos": 93,
      "nro": 142,
      "nombre": "OLIVERA Rodrigo",
      "anterior": 0.0,
      "serie": 0.0,
      "semif": 0.0,
      "prefinal": 0.0,
      "final": 0.0,
      "total": 0.0,
      "fin": null,
      "extras_raw": null
    },
    {
      "pos": 94,
      "nro": 156,
      "nombre": "TODINO Sebastian",
      "anterior": 0.0,
      "serie": 0.0,
      "semif": 0.0,
      "prefinal": 0.0,
      "final": 0.0,
      "total": 0.0,
      "fin": null,
      "extras_raw": null
    },
    {
      "pos": 95,
      "nro": 162,
      "nombre": "PERUGINI Juan",
      "anterior": 0.0,
      "serie": 0.0,
      "semif": 0.0,
      "prefinal": 0.0,
      "final": 0.0,
      "total": 0.0,
      "fin": null,
      "extras_raw": null
    }
  ]
}
