{
  "meta": {
    "source_pdf": "FECHA10.pdf",
    "extracted_at_utc": "2025-12-16T15:51:19+00:00",
    "fechas_cumplidas": 7,
    "fechas_detectadas": [
      7
    ]
  },
  "standings": [
    {
      "pos": 1,
      "nro": 2,
      "nombre": "FRANCHI Luciano 🏆🏆🏆🏆",
      "anterior": 109.5,
      "serie": 3.0,
      "semif": 8.0,
      "prefinal": 0.0,
      "final": 15.0,
      "total": 135.5,
      "fin": null,
      "extras_raw": "1 (04)"
    },
    {
      "pos": 2,
      "nro": 5,
      "nombre": "ALTAMIRANO Roy",
      "anterior": 102.5,
      "serie": 2.75,
      "semif": 7.0,
      "prefinal": 0.0,
      "final": 2.5,
      "total": 114.75,
      "fin": null,
      "extras_raw": "2 (02)"
    },
    {
      "pos": 3,
      "nro": 1,
      "nombre": "VALLEJOS Luciano 🏆",
      "anterior": 99.75,
      "serie": 2.75,
      "semif": 5.0,
      "prefinal": 0.0,
      "final": 7.0,
      "total": 114.5,
      "fin": null,
      "extras_raw": "1 (01)"
    },
    {
      "pos": 4,
      "nro": 21,
      "nombre": "SCHMIT Nahuel 🏆",
      "anterior": 88.5,
      "serie": 2.25,
      "semif": 3.5,
      "prefinal": 0.0,
      "final": 0.0,
      "total": 94.25,
      "fin": null,
      "extras_raw": "1 (01)"
    },
    {
      "pos": 5,
      "nro": 14,
      "nombre": "SALDAMANDO Fernando",
      "anterior": 71.25,
      "serie": 3.0,
      "semif": 8.0,
      "prefinal": 0.0,
      "final": 12.0,
      "total": 94.25,
      "fin": null,
      "extras_raw": "2 (01)"
    },
    {
      "pos": 6,
      "nro": 11,
      "nombre": "MANCINI Esteban",
      "anterior": 72.75,
      "serie": 2.5,
      "semif": 6.0,
      "prefinal": 0.0,
      "final": 4.0,
      "total": 85.25,
      "fin": null,
      "extras_raw": "2 (01)"
    },
    {
      "pos": 7,
      "nro": 30,
      "nombre": "RESOLA Johnatan",
      "anterior": 70.25,
      "serie": 2.5,
      "semif": 5.0,
      "prefinal": 0.0,
      "final": 4.5,
      "total": 82.25,
      "fin": null,
      "extras_raw": "3 (01)"
    },
    {
      "pos": 8,
      "nro": 9,
      "nombre": "OYOLA Matias Sebastian",
      "anterior": 69.5,
      "serie": 3.0,
      "semif": 8.0,
      "prefinal": 0.0,
      "final": 0.0,
      "total": 80.5,
      "fin": null,
      "extras_raw": "3 (01)"
    },
    {
      "pos": 9,
      "nro": 123,
      "nombre": "COLANERI Agustin",
      "anterior": 59.25,
      "serie": 2.75,
      "semif": 6.0,
      "prefinal": 0.0,
      "final": 5.0,
      "total": 73.0,
      "fin": null,
      "extras_raw": "6 (01)"
    },
    {
      "pos": 10,
      "nro": 22,
      "nombre": "BONIVARDO Fernando 🏆",
      "anterior": 67.25,
      "serie": 3.0,
      "semif": 0.0,
      "prefinal": 0.0,
      "final": 0.0,
      "total": 70.25,
      "fin": null,
      "extras_raw": "1 (01)"
    },
    {
      "pos": 11,
      "nro": 3,
      "nombre": "PEREZ MELER Agustin",
      "anterior": 51.5,
      "serie": 3.0,
      "semif": 7.0,
      "prefinal": 0.0,
      "final": 6.0,
      "total": 67.5,
      "fin": null,
      "extras_raw": "5 (01)"
    },
    {
      "pos": 12,
      "nro": 31,
      "nombre": "PUCCINELLI Carlos",
      "anterior": 52.5,
      "serie": 2.75,
      "semif": 4.0,
      "prefinal": 1.0,
      "final": 0.0,
      "total": 60.25,
      "fin": null,
      "extras_raw": "3 (01)"
    },
    {
      "pos": 13,
      "nro": 50,
      "nombre": "ANDRADE Joaquin",
      "anterior": 55.0,
      "serie": 2.5,
      "semif": 2.5,
      "prefinal": 0.0,
      "final": 0.0,
      "total": 60.0,
      "fin": null,
      "extras_raw": "7 (03)"
    },
    {
      "pos": 14,
      "nro": 4,
      "nombre": "ROTH Claudio",
      "anterior": 50.0,
      "serie": 3.0,
      "semif": 6.0,
      "prefinal": 0.0,
      "final": 0.0,
      "total": 59.0,
      "fin": null,
      "extras_raw": "6 (02)"
    },
    {
      "pos": 15,
      "nro": 19,
      "nombre": "TODINO Juan",
      "anterior": 46.0,
      "serie": 3.0,
      "semif": 8.0,
      "prefinal": 0.0,
      "final": 0.0,
      "total": 57.0,
      "fin": null,
      "extras_raw": "6 (01)"
    },
    {
      "pos": 16,
      "nro": 66,
      "nombre": "YUNGBLUT Valentin",
      "anterior": 49.5,
      "serie": 2.5,
      "semif": 2.5,
      "prefinal": 0.0,
      "final": 0.0,
      "total": 54.5,
      "fin": null,
      "extras_raw": "4 (01)"
    },
    {
      "pos": 17,
      "nro": 16,
      "nombre": "RODRIGUEZ Juan Cruz",
      "anterior": 51.0,
      "serie": 2.75,
      "semif": 0.5,
      "prefinal": 0.0,
      "final": 0.0,
      "total": 54.25,
      "fin": null,
      "extras_raw": "5 (01)"
    },
    {
      "pos": 18,
      "nro": 8,
      "nombre": "ALTAMIRANO Kevin",
      "anterior": 34.25,
      "serie": 2.75,
      "semif": 6.0,
      "prefinal": 0.0,
      "final": 10.0,
      "total": 53.0,
      "fin": null,
      "extras_raw": "3 (01)"
    },
    {
      "pos": 19,
      "nro": 39,
      "nombre": "PAGLIALUNGA Eros",
      "anterior": 37.0,
      "serie": 3.0,
      "semif": 7.0,
      "prefinal": 0.0,
      "final": 5.5,
      "total": 52.5,
      "fin": null,
      "extras_raw": "5 (01)"
    },
    {
      "pos": 20,
      "nro": 6,
      "nombre": "BURGOS Sebastian",
      "anterior": 48.5,
      "serie": 3.0,
      "semif": 0.0,
      "prefinal": 0.0,
      "final": 0.0,
      "total": 51.5,
      "fin": null,
      "extras_raw": "7 (01)"
    },
    {
      "pos": 21,
      "nro": 105,
      "nombre": "ZABALEGUI Martin",
      "anterior": 44.25,
      "serie": 2.25,
      "semif": 3.5,
      "prefinal": 0.0,
      "final": 0.0,
      "total": 50.0,
      "fin": null,
      "extras_raw": "2 (01)"
    },
    {
      "pos": 22,
      "nro": 20,
      "nombre": "PEREZ Sebastian",
      "anterior": null,
      "serie": 44.75,
      "semif": 2.25,
      "prefinal": 3.0,
      "final": 0.0,
      "total": 0.0,
      "fin": null,
      "extras_raw": "50.00 10 (01)"
    },
    {
      "pos": 23,
      "nro": 12,
      "nombre": "REY Javier",
      "anterior": null,
      "serie": 41.25,
      "semif": 2.5,
      "prefinal": 4.0,
      "final": 0.0,
      "total": 0.0,
      "fin": null,
      "extras_raw": "47.75 11 (01)"
    },
    {
      "pos": 24,
      "nro": 7,
      "nombre": "ROTH Ezequiel",
      "anterior": 42.5,
      "serie": 2.25,
      "semif": 2.0,
      "prefinal": 0.0,
      "final": 0.0,
      "total": 46.75,
      "fin": null,
      "extras_raw": "2 (01)"
    },
    {
      "pos": 25,
      "nro": 18,
      "nombre": "SCHIEBELBEIN Gabriel",
      "anterior": 41.25,
      "serie": 2.5,
      "semif": 3.0,
      "prefinal": 0.0,
      "final": 0.0,
      "total": 46.75,
      "fin": null,
      "extras_raw": "8 (01)"
    },
    {
      "pos": 26,
      "nro": 127,
      "nombre": "GRILL Lucas",
      "anterior": null,
      "serie": 34.75,
      "semif": 2.25,
      "prefinal": 4.0,
      "final": 0.0,
      "total": 3.5,
      "fin": null,
      "extras_raw": "44.50 10 (02)"
    },
    {
      "pos": 27,
      "nro": 23,
      "nombre": "PIÐEYRO Julio Cesar",
      "anterior": 30.75,
      "serie": 2.75,
      "semif": 5.0,
      "prefinal": 2.0,
      "final": 0.0,
      "total": 40.5,
      "fin": null,
      "extras_raw": "9 (01)"
    },
    {
      "pos": 28,
      "nro": 28,
      "nombre": "ANASTASIO Nicolas",
      "anterior": 30.25,
      "serie": 2.5,
      "semif": 3.5,
      "prefinal": 0.0,
      "final": 0.0,
      "total": 36.25,
      "fin": null,
      "extras_raw": "5 (01)"
    },
    {
      "pos": 29,
      "nro": 38,
      "nombre": "MADRIL Braian",
      "anterior": null,
      "serie": 31.5,
      "semif": 2.75,
      "prefinal": 1.0,
      "final": 0.0,
      "total": 0.0,
      "fin": null,
      "extras_raw": "35.25 11 (02)"
    },
    {
      "pos": 30,
      "nro": 24,
      "nombre": "AUSILI Marcelo",
      "anterior": null,
      "serie": 33.5,
      "semif": 1.75,
      "prefinal": 0.0,
      "final": 0.0,
      "total": 0.0,
      "fin": null,
      "extras_raw": "35.25 12 (01)"
    },
    {
      "pos": 31,
      "nro": 47,
      "nombre": "CUTINI Gustavo",
      "anterior": 25.75,
      "serie": 2.25,
      "semif": 7.0,
      "prefinal": 0.0,
      "final": 0.0,
      "total": 35.0,
      "fin": null,
      "extras_raw": "3 (01)"
    },
    {
      "pos": 32,
      "nro": 33,
      "nombre": "CAPUTO Nicolas",
      "anterior": null,
      "serie": 31.75,
      "semif": 2.5,
      "prefinal": 0.0,
      "final": 0.0,
      "total": 0.0,
      "fin": null,
      "extras_raw": "34.25 12 (01)"
    },
    {
      "pos": 33,
      "nro": 56,
      "nombre": "CHIAPARO Nicolas",
      "anterior": 31.75,
      "serie": 2.25,
      "semif": 0.0,
      "prefinal": 0.0,
      "final": 0.0,
      "total": 34.0,
      "fin": null,
      "extras_raw": "9 (01)"
    },
    {
      "pos": 34,
      "nro": 102,
      "nombre": "TORRES Luciano",
      "anterior": 26.25,
      "serie": 3.0,
      "semif": 4.0,
      "prefinal": 0.0,
      "final": 0.0,
      "total": 33.25,
      "fin": null,
      "extras_raw": "6 (01)"
    },
    {
      "pos": 35,
      "nro": 26,
      "nombre": "BREZINA Gonzalo",
      "anterior": null,
      "serie": 27.75,
      "semif": 2.5,
      "prefinal": 1.0,
      "final": 0.0,
      "total": 0.0,
      "fin": null,
      "extras_raw": "31.25 12 (01)"
    },
    {
      "pos": 36,
      "nro": 48,
      "nombre": "YUROVSKY Guillermo",
      "anterior": 23.0,
      "serie": 2.75,
      "semif": 2.0,
      "prefinal": 0.0,
      "final": 0.0,
      "total": 27.75,
      "fin": null,
      "extras_raw": "6 (01)"
    },
    {
      "pos": 37,
      "nro": 51,
      "nombre": "ONORATO Nicolas",
      "anterior": 22.25,
      "serie": 3.0,
      "semif": 2.0,
      "prefinal": 0.0,
      "final": 0.0,
      "total": 27.25,
      "fin": null,
      "extras_raw": "6 (01)"
    },
    {
      "pos": 38,
      "nro": 36,
      "nombre": "MACAZAGA Nicolas",
      "anterior": 21.0,
      "serie": 2.75,
      "semif": 3.5,
      "prefinal": 0.0,
      "final": 0.0,
      "total": 27.25,
      "fin": 25,
      "extras_raw": null
    },
    {
      "pos": 39,
      "nro": 46,
      "nombre": "DUPONT Braian",
      "anterior": null,
      "serie": 15.75,
      "semif": 2.75,
      "prefinal": 5.0,
      "final": 0.0,
      "total": 3.0,
      "fin": null,
      "extras_raw": "26.50 11 (01)"
    },
    {
      "pos": 40,
      "nro": 104,
      "nombre": "HARDOY Maximiliano",
      "anterior": 22.0,
      "serie": 1.75,
      "semif": 0.0,
      "prefinal": 0.0,
      "final": 0.0,
      "total": 23.75,
      "fin": 75,
      "extras_raw": null
    },
    {
      "pos": 41,
      "nro": 116,
      "nombre": "ZUBELDIA Rodrigo",
      "anterior": 22.0,
      "serie": 0.5,
      "semif": 0.0,
      "prefinal": 0.0,
      "final": 0.0,
      "total": 22.5,
      "fin": null,
      "extras_raw": "3 (01)"
    },
    {
      "pos": 42,
      "nro": 34,
      "nombre": "DAILOFF Nehuen",
      "anterior": 20.5,
      "serie": 2.0,
      "semif": 0.0,
      "prefinal": 0.0,
      "final": 0.0,
      "total": 22.5,
      "fin": 50,
      "extras_raw": null
    },
    {
      "pos": 43,
      "nro": 57,
      "nombre": "RAZQUIN Gonzalo",
      "anterior": 20.5,
      "serie": 1.75,
      "semif": 0.0,
      "prefinal": 0.0,
      "final": 0.0,
      "total": 22.25,
      "fin": null,
      "extras_raw": "9 (01)"
    },
    {
      "pos": 44,
      "nro": 88,
      "nombre": "SOTO Juan Maria",
      "anterior": 18.25,
      "serie": 2.5,
      "semif": 1.0,
      "prefinal": 0.0,
      "final": 0.0,
      "total": 21.75,
      "fin": null,
      "extras_raw": "2 (01)"
    },
    {
      "pos": 45,
      "nro": 60,
      "nombre": "MOYANO Antonio",
      "anterior": 16.5,
      "serie": 1.5,
      "semif": 3.0,
      "prefinal": 0.0,
      "final": 0.0,
      "total": 21.0,
      "fin": null,
      "extras_raw": "8 (01)"
    },
    {
      "pos": 46,
      "nro": 111,
      "nombre": "BRAY Juan P",
      "anterior": 15.75,
      "serie": 2.25,
      "semif": 2.5,
      "prefinal": 0.0,
      "final": 0.0,
      "total": 20.5,
      "fin": 50,
      "extras_raw": null
    },
    {
      "pos": 47,
      "nro": 29,
      "nombre": "GARCIA Joaquin",
      "anterior": 16.75,
      "serie": 2.0,
      "semif": 1.5,
      "prefinal": 0.0,
      "final": 0.0,
      "total": 20.25,
      "fin": 25,
      "extras_raw": null
    },
    {
      "pos": 48,
      "nro": 25,
      "nombre": "PALMA Nicolas",
      "anterior": 17.75,
      "serie": 1.75,
      "semif": 0.0,
      "prefinal": 0.0,
      "final": 0.0,
      "total": 19.5,
      "fin": 50,
      "extras_raw": null
    },
    {
      "pos": 49,
      "nro": 75,
      "nombre": "BENITEZ Gaston",
      "anterior": 18.0,
      "serie": 1.5,
      "semif": 0.0,
      "prefinal": 0.0,
      "final": 0.0,
      "total": 19.5,
      "fin": 50,
      "extras_raw": null
    },
    {
      "pos": 50,
      "nro": 53,
      "nombre": "PASCUAL Emanuel",
      "anterior": 14.25,
      "serie": 2.0,
      "semif": 3.0,
      "prefinal": 0.0,
      "final": 0.0,
      "total": 19.25,
      "fin": 25,
      "extras_raw": null
    },
    {
      "pos": 51,
      "nro": 15,
      "nombre": "HIDALGO Federico",
      "anterior": null,
      "serie": 15.5,
      "semif": 1.75,
      "prefinal": 1.5,
      "final": 0.0,
      "total": 0.0,
      "fin": null,
      "extras_raw": "18.75 12 (01)"
    },
    {
      "pos": 52,
      "nro": 137,
      "nombre": "DAILOFF Ramiro",
      "anterior": 16.25,
      "serie": 1.75,
      "semif": 0.0,
      "prefinal": 0.0,
      "final": 0.0,
      "total": 18.0,
      "fin": null,
      "extras_raw": "4 (01)"
    },
    {
      "pos": 53,
      "nro": 27,
      "nombre": "AUSILI Agustin",
      "anterior": 16.25,
      "serie": 1.75,
      "semif": 0.0,
      "prefinal": 0.0,
      "final": 0.0,
      "total": 18.0,
      "fin": 0,
      "extras_raw": null
    },
    {
      "pos": 54,
      "nro": 13,
      "nombre": "ROUAIX Javier",
      "anterior": 17.0,
      "serie": 0.0,
      "semif": 0.0,
      "prefinal": 0.0,
      "final": 0.0,
      "total": 17.0,
      "fin": null,
      "extras_raw": "2 (01)"
    },
    {
      "pos": 55,
      "nro": 45,
      "nombre": "PETRACCI Gaston",
      "anterior": 17.0,
      "serie": 0.0,
      "semif": 0.0,
      "prefinal": 0.0,
      "final": 0.0,
      "total": 17.0,
      "fin": null,
      "extras_raw": "5 (01)"
    },
    {
      "pos": 56,
      "nro": 69,
      "nombre": "OVEJERO Facundo",
      "anterior": 13.5,
      "serie": 2.5,
      "semif": 0.5,
      "prefinal": 0.0,
      "final": 0.0,
      "total": 16.5,
      "fin": 50,
      "extras_raw": null
    },
    {
      "pos": 57,
      "nro": 134,
      "nombre": "MONTANARI Nicolas",
      "anterior": 12.0,
      "serie": 2.25,
      "semif": 2.0,
      "prefinal": 0.0,
      "final": 0.0,
      "total": 16.25,
      "fin": null,
      "extras_raw": "3 (01)"
    },
    {
      "pos": 58,
      "nro": 112,
      "nombre": "GOMEZ Agustin",
      "anterior": 14.0,
      "serie": 2.0,
      "semif": 0.0,
      "prefinal": 0.0,
      "final": 0.0,
      "total": 16.0,
      "fin": 0,
      "extras_raw": null
    },
    {
      "pos": 59,
      "nro": 65,
      "nombre": "ALZA Pablo",
      "anterior": 14.5,
      "serie": 1.5,
      "semif": 0.0,
      "prefinal": 0.0,
      "final": 0.0,
      "total": 16.0,
      "fin": 0,
      "extras_raw": null
    },
    {
      "pos": 60,
      "nro": 95,
      "nombre": "PALLOTTI Ivan",
      "anterior": 15.0,
      "serie": 0.0,
      "semif": 0.0,
      "prefinal": 0.0,
      "final": 0.0,
      "total": 15.0,
      "fin": null,
      "extras_raw": "4 (01)"
    },
    {
      "pos": 61,
      "nro": 40,
      "nombre": "BALDUCHI Valentin",
      "anterior": 14.5,
      "serie": 0.0,
      "semif": 0.0,
      "prefinal": 0.0,
      "final": 0.0,
      "total": 14.5,
      "fin": 50,
      "extras_raw": null
    },
    {
      "pos": 62,
      "nro": 156,
      "nombre": "TODINO Sebastian",
      "anterior": 12.0,
      "serie": 2.0,
      "semif": 0.0,
      "prefinal": 0.0,
      "final": 0.0,
      "total": 14.0,
      "fin": 0,
      "extras_raw": null
    },
    {
      "pos": 63,
      "nro": 96,
      "nombre": "BECCHIO Martin",
      "anterior": 11.75,
      "serie": 1.75,
      "semif": 0.0,
      "prefinal": 0.0,
      "final": 0.0,
      "total": 13.5,
      "fin": 50,
      "extras_raw": null
    },
    {
      "pos": 64,
      "nro": 32,
      "nombre": "MELGER Julian",
      "anterior": 11.25,
      "serie": 2.0,
      "semif": 0.0,
      "prefinal": 0.0,
      "final": 0.0,
      "total": 13.25,
      "fin": 25,
      "extras_raw": null
    },
    {
      "pos": 65,
      "nro": 54,
      "nombre": "TOLEDO Joaquin",
      "anterior": 8.5,
      "serie": 2.25,
      "semif": 2.5,
      "prefinal": 0.0,
      "final": 0.0,
      "total": 13.25,
      "fin": 25,
      "extras_raw": null
    },
    {
      "pos": 66,
      "nro": 43,
      "nombre": "COLTURI Fabian",
      "anterior": 9.5,
      "serie": 2.0,
      "semif": 1.5,
      "prefinal": 0.0,
      "final": 0.0,
      "total": 13.0,
      "fin": 0,
      "extras_raw": null
    },
    {
      "pos": 67,
      "nro": 72,
      "nombre": "JACOB Ruben",
      "anterior": 11.0,
      "serie": 1.5,
      "semif": 0.0,
      "prefinal": 0.0,
      "final": 0.0,
      "total": 12.5,
      "fin": 50,
      "extras_raw": null
    },
    {
      "pos": 68,
      "nro": 76,
      "nombre": "LOPEZ Braian",
      "anterior": 12.25,
      "serie": 0.0,
      "semif": 0.0,
      "prefinal": 0.0,
      "final": 0.0,
      "total": 12.25,
      "fin": 25,
      "extras_raw": null
    },
    {
      "pos": 69,
      "nro": 98,
      "nombre": "FRITZ Jorge",
      "anterior": 9.75,
      "serie": 2.25,
      "semif": 0.0,
      "prefinal": 0.0,
      "final": 0.0,
      "total": 12.0,
      "fin": 0,
      "extras_raw": null
    },
    {
      "pos": 70,
      "nro": 94,
      "nombre": "CHIESA Alejandro",
      "anterior": 10.25,
      "serie": 1.5,
      "semif": 0.0,
      "prefinal": 0.0,
      "final": 0.0,
      "total": 11.75,
      "fin": 75,
      "extras_raw": null
    },
    {
      "pos": 71,
      "nro": 44,
      "nombre": "MARCOS Nehuen",
      "anterior": 11.5,
      "serie": 0.0,
      "semif": 0.0,
      "prefinal": 0.0,
      "final": 0.0,
      "total": 11.5,
      "fin": 50,
      "extras_raw": null
    },
    {
      "pos": 72,
      "nro": 79,
      "nombre": "LUCERO Sebastian",
      "anterior": 9.5,
      "serie": 1.75,
      "semif": 0.0,
      "prefinal": 0.0,
      "final": 0.0,
      "total": 11.25,
      "fin": 25,
      "extras_raw": null
    },
    {
      "pos": 73,
      "nro": 55,
      "nombre": "ANTINORI Axel",
      "anterior": 10.5,
      "serie": 0.5,
      "semif": 0.0,
      "prefinal": 0.0,
      "final": 0.0,
      "total": 11.0,
      "fin": null,
      "extras_raw": "6 (01)"
    },
    {
      "pos": 74,
      "nro": 41,
      "nombre": "CUTINI SAMOSIUK Santino",
      "anterior": 9.25,
      "serie": 1.75,
      "semif": 0.0,
      "prefinal": 0.0,
      "final": 0.0,
      "total": 11.0,
      "fin": 0,
      "extras_raw": null
    },
    {
      "pos": 75,
      "nro": 86,
      "nombre": "SALAZAR Alfredo",
      "anterior": 9.5,
      "serie": 1.5,
      "semif": 0.0,
      "prefinal": 0.0,
      "final": 0.0,
      "total": 11.0,
      "fin": 0,
      "extras_raw": null
    },
    {
      "pos": 76,
      "nro": 67,
      "nombre": "HOCK Gaston",
      "anterior": 8.75,
      "serie": 2.0,
      "semif": 0.0,
      "prefinal": 0.0,
      "final": 0.0,
      "total": 10.75,
      "fin": 75,
      "extras_raw": null
    },
    {
      "pos": 77,
      "nro": 110,
      "nombre": "FORD Lautaro",
      "anterior": 10.5,
      "serie": 0.0,
      "semif": 0.0,
      "prefinal": 0.0,
      "final": 0.0,
      "total": 10.5,
      "fin": 50,
      "extras_raw": null
    },
    {
      "pos": 78,
      "nro": 113,
      "nombre": "MARCO Gabriel",
      "anterior": 9.0,
      "serie": 1.5,
      "semif": 0.0,
      "prefinal": 0.0,
      "final": 0.0,
      "total": 10.5,
      "fin": 50,
      "extras_raw": null
    },
    {
      "pos": 79,
      "nro": 58,
      "nombre": "PEREZ Marcelo",
      "anterior": 8.25,
      "serie": 2.0,
      "semif": 0.0,
      "prefinal": 0.0,
      "final": 0.0,
      "total": 10.25,
      "fin": 25,
      "extras_raw": null
    },
    {
      "pos": 80,
      "nro": 142,
      "nombre": "OLIVERA Rodrigo",
      "anterior": 10.0,
      "serie": 0.0,
      "semif": 0.0,
      "prefinal": 0.0,
      "final": 0.0,
      "total": 10.0,
      "fin": 0,
      "extras_raw": null
    },
    {
      "pos": 81,
      "nro": 109,
      "nombre": "ANASTASIO Diego",
      "anterior": 7.5,
      "serie": 2.0,
      "semif": 0.0,
      "prefinal": 0.0,
      "final": 0.0,
      "total": 9.5,
      "fin": 50,
      "extras_raw": null
    },
    {
      "pos": 82,
      "nro": 114,
      "nombre": "CALVO Juan Ignacio",
      "anterior": 7.25,
      "serie": 2.0,
      "semif": 0.0,
      "prefinal": 0.0,
      "final": 0.0,
      "total": 9.25,
      "fin": 25,
      "extras_raw": null
    },
    {
      "pos": 83,
      "nro": 81,
      "nombre": "CALVO Jose Maria",
      "anterior": 7.25,
      "serie": 1.5,
      "semif": 0.0,
      "prefinal": 0.0,
      "final": 0.0,
      "total": 8.75,
      "fin": 75,
      "extras_raw": null
    },
    {
      "pos": 84,
      "nro": 35,
      "nombre": "MORENO Maximiliano",
      "anterior": 7.5,
      "serie": 0.0,
      "semif": 0.0,
      "prefinal": 0.0,
      "final": 0.0,
      "total": 7.5,
      "fin": 50,
      "extras_raw": null
    },
    {
      "pos": 85,
      "nro": 78,
      "nombre": "GONZALEZ Juan I",
      "anterior": 7.25,
      "serie": 0.0,
      "semif": 0.0,
      "prefinal": 0.0,
      "final": 0.0,
      "total": 7.25,
      "fin": 25,
      "extras_raw": null
    },
    {
      "pos": 86,
      "nro": 63,
      "nombre": "JACA Aaron",
      "anterior": 4.75,
      "serie": 1.75,
      "semif": 0.0,
      "prefinal": 0.0,
      "final": 0.0,
      "total": 6.5,
      "fin": 50,
      "extras_raw": null
    },
    {
      "pos": 87,
      "nro": 49,
      "nombre": "PERUGINI Flavio",
      "anterior": 6.25,
      "serie": 0.0,
      "semif": 0.0,
      "prefinal": 0.0,
      "final": 0.0,
      "total": 6.25,
      "fin": 25,
      "extras_raw": null
    },
    {
      "pos": 88,
      "nro": 74,
      "nombre": "MANZOTTI Gustavo",
      "anterior": 6.25,
      "serie": 0.0,
      "semif": 0.0,
      "prefinal": 0.0,
      "final": 0.0,
      "total": 6.25,
      "fin": 25,
      "extras_raw": null
    },
    {
      "pos": 89,
      "nro": 108,
      "nombre": "FORNERON Carlos",
      "anterior": 5.5,
      "serie": 0.0,
      "semif": 0.0,
      "prefinal": 0.0,
      "final": 0.0,
      "total": 5.5,
      "fin": 50,
      "extras_raw": null
    },
    {
      "pos": 90,
      "nro": 162,
      "nombre": "PERUGINI Juan Francisco",
      "anterior": 3.75,
      "serie": 0.0,
      "semif": 0.0,
      "prefinal": 0.0,
      "final": 0.0,
      "total": 3.75,
      "fin": 75,
      "extras_raw": null
    },
    {
      "pos": 91,
      "nro": 115,
      "nombre": "LOPEZ Agustin",
      "anterior": 3.5,
      "serie": 0.0,
      "semif": 0.0,
      "prefinal": 0.0,
      "final": 0.0,
      "total": 3.5,
      "fin": 50,
      "extras_raw": null
    },
    {
      "pos": 92,
      "nro": 97,
      "nombre": "SOTO Gaston",
      "anterior": 1.5,
      "serie": 0.0,
      "semif": 0.0,
      "prefinal": 0.0,
      "final": 0.0,
      "total": 1.5,
      "fin": 50,
      "extras_raw": null
    }
  ]
}
